src/__init__.py
src/homeio.py
homeio-1.0.2.dist-info/METADATA
homeio-1.0.2.dist-info/WHEEL
homeio-1.0.2.dist-info/licenses/LICENSE
homeio-1.0.2.dist-info/RECORD
