Metadata-Version: 2.3
Name: homeio
Version: 1.0.2
Summary: A module to interact with Home I/O (NOTE: the readme is incorrect of many things lol)
Author-email: Gabriel Bourneau <11.gabriel.bourneau@lafase.cl>
License-File: LICENSE
Classifier: Operating System :: OS Independent
Classifier: Programming Language :: Python :: 3
Requires-Python: >=3.8
